setup.cfg
setup.py
sysdig_tracers.py
sysdig_tracers.egg-info/PKG-INFO
sysdig_tracers.egg-info/SOURCES.txt
sysdig_tracers.egg-info/dependency_links.txt
sysdig_tracers.egg-info/not-zip-safe
sysdig_tracers.egg-info/top_level.txt