Metadata-Version: 1.0
Name: sysdig-tracers
Version: 0.1.1
Summary: Python library to emit Sysdig tracers
Home-page: http://github.com/draios/tracers-py
Author: sysdig Inc.
Author-email: info@sysdig.com
License: MIT
Platform: UNKNOWN
